soundpad/__init__.py
soundpad/_version.py
soundpad/soundpad.py
soundpad-0.9.1.dist-info/LICENSE
soundpad-0.9.1.dist-info/METADATA
soundpad-0.9.1.dist-info/WHEEL
soundpad-0.9.1.dist-info/entry_points.txt
soundpad-0.9.1.dist-info/top_level.txt
soundpad-0.9.1.dist-info/RECORD
