Metadata-Version: 2.1
Name: soundpad
Version: 0.9.1
Summary: A small tool to use a novation launchpad mini as soundboard.
Home-page: https://github.com/mutax/soundpad
Author: Florian Streibelt
Author-email: pypi@streibelt.net
License: UNKNOWN
Platform: UNKNOWN
Classifier: Programming Language :: Python :: 3
Classifier: License :: OSI Approved :: MIT License
Classifier: Operating System :: OS Independent
Requires-Python: >=3.5
Requires-Dist: launchpad-py
Requires-Dist: pygame
